viewtext_c/__init__.py
viewtext_c/__main__.py
viewtext_c/color.py
viewtext_c/color_list.py
viewtext_c/const.py
viewtext_c/globyl.py
viewtext_c/paint.py
viewtext_c/pane.py
viewtext_c/resources/__init__.py
viewtext_c/resources/config.toml
viewtext_c/search.py
viewtext_c/stack.py
viewtext_c/stryng.py
viewtext_c/util.py
viewtext_c/util_io.py
viewtext_curses-1.2.6.dist-info/LICENSE
viewtext_curses-1.2.6.dist-info/METADATA
viewtext_curses-1.2.6.dist-info/WHEEL
viewtext_curses-1.2.6.dist-info/entry_points.txt
viewtext_curses-1.2.6.dist-info/RECORD
