Metadata-Version: 2.1
Name: viewtext-curses
Version: 1.2.6
Summary: Curses-based text file viewer
Home-page: https://github.com/JoeRodrigue/viewtext-curses
License: Apache-2.0
Keywords: textfile,viewer
Author: Joe Rodrigue
Author-email: joe.rodrigue@gmail.com
Maintainer: Joe Rodrigue
Maintainer-email: joe.rodrigue@gmail.com
Requires-Python: >=3.10,<4.0
Classifier: License :: OSI Approved :: Apache Software License
Classifier: Operating System :: OS Independent
Classifier: Programming Language :: Python :: 3
Classifier: Programming Language :: Python :: 3.10
Classifier: Programming Language :: Python :: 3.11
Classifier: Programming Language :: Python :: 3.12
Requires-Dist: click (>=2.0)
Requires-Dist: tomli_w (>=1.0.0,<2.0.0)
Project-URL: Documentation, https://github.com/JoeRodrigue/viewtext-curses
Project-URL: Repository, https://github.com/JoeRodrigue/viewtext-curses
